terapilot/__init__.py
terapilot/cli.py
terapilot/utils.py
terapilot-1.0.3.dist-info/METADATA
terapilot-1.0.3.dist-info/WHEEL
terapilot-1.0.3.dist-info/entry_points.txt
terapilot-1.0.3.dist-info/top_level.txt
terapilot-1.0.3.dist-info/RECORD
