Metadata-Version: 2.4
Name: terapilot
Version: 1.0.3
Requires-Python: >=3.6
Requires-Dist: cohere>=4.0
Requires-Dist: requests>=2.25
Requires-Dist: python-dotenv>=0.19
Requires-Dist: pathlib>=1.0; python_version < "3.4"
Dynamic: requires-dist
Dynamic: requires-python
